[
    {
        "locale": "en-US",
        "title": "League of Legends - Esports News"
    },
    {
        "locale": "en-GB",
        "title": "League of Legends - Esports News"
    },
    {
        "locale": "de-DE",
        "title": "League of Legends - Esports News"
    },
    {
        "locale": "es-ES",
        "title": "League of Legends - Noticias de eSports"
    },
    {
        "locale": "es-MX",
        "title": "League of Legends - Noticias de eSports"
    },
    {
        "locale": "fr-FR",
        "title": "League of Legends - Nouvelles eSports"
    },
    {
        "locale": "it-IT",
        "title": "League of Legends - Notizie eSports"
    },
    {
        "locale": "pl-PL",
        "title": "League of Legends - Wiadomości e-sportowe"
    },
    {
        "locale": "pt-BR",
        "title": "League of Legends - Notícias eSports"
    },
    {
        "locale": "ru-RU",
        "title": "League of Legends - Новости киберспорта"
    },
    {
        "locale": "tr-TR",
        "title": "League of Legends - Esports Haberleri"
    },
    {
        "locale": "ja-JP",
        "title": "リーグ・オブ・レジェンド - Eスポーツニュース"
    },
    {
        "locale": "ko-KR",
        "title": "리그 오브 레전드 - 스포츠 뉴스"
    },
    {
        "locale": "zh-TW",
        "title": "League of Legends - Esports News"
    },
    {
        "locale": "th-TH",
        "title": "League of Legends - Esports News"
    },
    {
        "locale": "en-PH",
        "title": "League of Legends - Esports News"
    },
    {
        "locale": "en-SG",
        "title": "League of Legends - Esports News"
    }
]
