[
    {
        "locale": "en-US",
        "title": "League of Legends: Wild Rift - Esports News"
    },
    {
        "locale": "en-GB",
        "title": "League of Legends: Wild Rift - Esports News"
    },
    {
        "locale": "en-AU",
        "title": "League of Legends: Wild Rift - Esports News"
    },
    {
        "locale": "cs-CZ",
        "title": "League of Legends: Wild Rift - Esports News"
    },
    {
        "locale": "de-DE",
        "title": "League of Legends: Wild Rift - Esports News"
    },
    {
        "locale": "el-GR",
        "title": "League of Legends: Wild Rift - Esports News"
    },
    {
        "locale": "es-ES",
        "title": "League of Legends: Wild Rift - Noticias de eSports"
    },
    {
        "locale": "es-MX",
        "title": "League of Legends: Wild Rift - Noticias de eSports"
    },
    {
        "locale": "fr-FR",
        "title": "League of Legends: Wild Rift - Nouvelles eSports"
    },
    {
        "locale": "it-IT",
        "title": "League of Legends: Wild Rift - Notizie eSports"
    },
    {
        "locale": "pl-PL",
        "title": "League of Legends: Wild Rift - Wiadomości e-sportowe"
    },
    {
        "locale": "pt-BR",
        "title": "League of Legends: Wild Rift - Notícias eSports"
    },
    {
        "locale": "ro-RO",
        "title": "League of Legends: Wild Rift - Esports News"
    },
    {
        "locale": "ru-RU",
        "title": "League of Legends: Wild Rift - Новости киберспорта"
    },
    {
        "locale": "tr-TR",
        "title": "League of Legends: Wild Rift - Esports Haberleri"
    },
    {
        "locale": "ja-JP",
        "title": "League of Legends: Wild Rift - Eスポーツニュース"
    },
    {
        "locale": "ko-KR",
        "title": "League of Legends: Wild Rift - 스포츠 뉴스"
    },
    {
        "locale": "zh-TW",
        "title": "League of Legends: Wild Rift - Esports News"
    },
    {
        "locale": "th-TH",
        "title": "League of Legends: Wild Rift - Esports News"
    },
    {
        "locale": "en-PH",
        "title": "League of Legends: Wild Rift - Esports News"
    },
    {
        "locale": "en-SG",
        "title": "League of Legends: Wild Rift - Esports News"
    },
    {
        "locale": "id-ID",
        "title": "League of Legends: Wild Rift - Esports News"
    },
    {
        "locale": "vi-VN",
        "title": "League of Legends: Wild Rift - Esports News"
    }
]
